datasette_alerts/__init__.py
datasette_alerts/hookspecs.py
datasette_alerts/internal_migrations.py
datasette_alerts/templates/tmp.html
datasette_alerts-0.0.1a6.dist-info/licenses/LICENSE
examples/federal-register/cli.py
examples/sample-notifiers/desktop.py
examples/sample-notifiers/discord.py
examples/sample-notifiers/ntfy.py
examples/sample-notifiers/slack.py
tests/test_alerts.py
datasette_alerts-0.0.1a6.dist-info/METADATA
datasette_alerts-0.0.1a6.dist-info/WHEEL
datasette_alerts-0.0.1a6.dist-info/entry_points.txt
datasette_alerts-0.0.1a6.dist-info/top_level.txt
datasette_alerts-0.0.1a6.dist-info/RECORD
