Metadata-Version: 2.4
Name: datasette-alerts
Version: 0.0.1a6
Summary: Setup alerts on specfic new records.
Author: Alex Garcia
License-Expression: Apache-2.0
Project-URL: Homepage, https://github.com/datasette/datasette-alerts
Project-URL: Changelog, https://github.com/datasette/datasette-alerts/releases
Project-URL: Issues, https://github.com/datasette/datasette-alerts/issues
Project-URL: CI, https://github.com/datasette/datasette-alerts/actions
Classifier: Framework :: Datasette
Requires-Python: >=3.10
License-File: LICENSE
Requires-Dist: datasette>=1.0a21
Requires-Dist: pydantic>=2
Requires-Dist: python-ulid>=3
Requires-Dist: sqlite-migrate>=0.1b0
Requires-Dist: sqlite-utils>=3.38
Requires-Dist: wtforms>=3.2.1
Provides-Extra: test
Requires-Dist: pytest; extra == "test"
Requires-Dist: pytest-asyncio; extra == "test"
Dynamic: license-file
